{
  "$schema": "https://developer.microsoft.com/json-schemas/fabric/item/report/definition/visualContainer/2.5.0/schema.json",
  "name": "f2eada01d5d4ad932c68",
  "position": {
    "x": 118.22900763358778,
    "y": 151.45038167938932,
    "z": 3012,
    "height": 149.49618320610688,
    "width": 485.618320610687,
    "tabOrder": 5012
  },
  "visual": {
    "visualType": "lineChart",
    "query": {
      "queryState": {
        "Category": {
          "projections": [
            {
              "field": {
                "HierarchyLevel": {
                  "Expression": {
                    "Hierarchy": {
                      "Expression": {
                        "PropertyVariationSource": {
                          "Expression": {
                            "SourceRef": {
                              "Entity": "dim_fecha"
                            }
                          },
                          "Name": "Variación",
                          "Property": "FullDate"
                        }
                      },
                      "Hierarchy": "Jerarquía de fechas"
                    }
                  },
                  "Level": "Año"
                }
              },
              "queryRef": "dim_fecha.FullDate.Variación.Jerarquía de fechas.Año",
              "nativeQueryRef": "FullDate Año",
              "active": true
            },
            {
              "field": {
                "HierarchyLevel": {
                  "Expression": {
                    "Hierarchy": {
                      "Expression": {
                        "PropertyVariationSource": {
                          "Expression": {
                            "SourceRef": {
                              "Entity": "dim_fecha"
                            }
                          },
                          "Name": "Variación",
                          "Property": "FullDate"
                        }
                      },
                      "Hierarchy": "Jerarquía de fechas"
                    }
                  },
                  "Level": "Mes"
                }
              },
              "queryRef": "dim_fecha.FullDate.Variación.Jerarquía de fechas.Mes",
              "nativeQueryRef": "FullDate Mes",
              "active": true
            }
          ]
        },
        "Y": {
          "projections": [
            {
              "field": {
                "Measure": {
                  "Expression": {
                    "SourceRef": {
                      "Entity": "fact_ventas"
                    }
                  },
                  "Property": "ventas totales"
                }
              },
              "queryRef": "fact_ventas.ventas totales",
              "nativeQueryRef": "ventas totales"
            }
          ]
        }
      }
    },
    "objects": {
      "dataPoint": [
        {
          "properties": {
            "fill": {
              "solid": {
                "color": {
                  "expr": {
                    "Literal": {
                      "Value": "'#1F3A5F'"
                    }
                  }
                }
              }
            }
          },
          "selector": {
            "metadata": "fact_ventas.ventas totales"
          }
        }
      ],
      "lineStyles": [
        {
          "properties": {
            "strokeWidth": {
              "expr": {
                "Literal": {
                  "Value": "2D"
                }
              }
            },
            "lineStyle": {
              "expr": {
                "Literal": {
                  "Value": "'solid'"
                }
              }
            }
          }
        }
      ],
      "categoryAxis": [
        {
          "properties": {
            "invertAxis": {
              "expr": {
                "Literal": {
                  "Value": "false"
                }
              }
            },
            "labelDisplayUnits": {
              "expr": {
                "Literal": {
                  "Value": "0D"
                }
              }
            },
            "show": {
              "expr": {
                "Literal": {
                  "Value": "true"
                }
              }
            }
          }
        }
      ],
      "valueAxis": [
        {
          "properties": {
            "show": {
              "expr": {
                "Literal": {
                  "Value": "false"
                }
              }
            },
            "showAxisTitle": {
              "expr": {
                "Literal": {
                  "Value": "false"
                }
              }
            }
          }
        }
      ],
      "forecast": [
        {
          "properties": {
            "show": {
              "expr": {
                "Literal": {
                  "Value": "true"
                }
              }
            },
            "displayName": {
              "expr": {
                "Literal": {
                  "Value": "'Previsión siguientes 6 meses'"
                }
              }
            },
            "transform": {
              "algorithm": "Forecast",
              "parameters": [
                {
                  "Literal": {
                    "Value": "7D"
                  },
                  "Name": "Unit"
                },
                {
                  "Literal": {
                    "Value": "10D"
                  },
                  "Name": "ForecastLength"
                },
                {
                  "Literal": {
                    "Value": "0D"
                  },
                  "Name": "IgnoreLast"
                },
                {
                  "Literal": {
                    "Value": "0.95D"
                  },
                  "Name": "ConfidenceLevel"
                }
              ]
            },
            "bandAreaColor": {
              "solid": {
                "color": {
                  "expr": {
                    "Literal": {
                      "Value": "'#F2994A'"
                    }
                  }
                }
              }
            },
            "bandAreaTransparency": {
              "expr": {
                "Literal": {
                  "Value": "69D"
                }
              }
            },
            "lineColor": {
              "solid": {
                "color": {
                  "expr": {
                    "ThemeDataColor": {
                      "ColorId": 4,
                      "Percent": 0
                    }
                  }
                }
              }
            },
            "style": {
              "expr": {
                "Literal": {
                  "Value": "'solid'"
                }
              }
            },
            "bandLineShow": {
              "expr": {
                "Literal": {
                  "Value": "false"
                }
              }
            },
            "bandLineTransparency": {
              "expr": {
                "Literal": {
                  "Value": "0D"
                }
              }
            },
            "interpolation": {
              "expr": {
                "Literal": {
                  "Value": "'linear'"
                }
              }
            }
          },
          "selector": {
            "metadata": "fact_ventas.ventas totales",
            "id": "1"
          }
        }
      ],
      "trend": [
        {
          "properties": {
            "show": {
              "expr": {
                "Literal": {
                  "Value": "true"
                }
              }
            },
            "displayName": {
              "expr": {
                "Literal": {
                  "Value": "'Línea de tendencia 1'"
                }
              }
            },
            "lineColor": {
              "solid": {
                "color": {
                  "expr": {
                    "Literal": {
                      "Value": "'#2F80ED'"
                    }
                  }
                }
              }
            },
            "width": {
              "expr": {
                "Literal": {
                  "Value": "2D"
                }
              }
            }
          }
        }
      ]
    },
    "visualContainerObjects": {
      "background": [
        {
          "properties": {
            "show": {
              "expr": {
                "Literal": {
                  "Value": "false"
                }
              }
            }
          }
        }
      ],
      "title": [
        {
          "properties": {
            "text": {
              "expr": {
                "Literal": {
                  "Value": "'Evolución Histórica de Ventas'"
                }
              }
            },
            "fontFamily": {
              "expr": {
                "Literal": {
                  "Value": "'''Segoe UI'', wf_segoe-ui_normal, helvetica, arial, sans-serif'"
                }
              }
            },
            "fontSize": {
              "expr": {
                "Literal": {
                  "Value": "12D"
                }
              }
            }
          }
        }
      ]
    },
    "drillFilterOtherVisuals": true
  }
}