{
  "$schema": "https://developer.microsoft.com/json-schemas/fabric/item/report/definition/bookmark/2.0.0/schema.json",
  "displayName": "Cerrar menú ventas",
  "name": "8d6cf1aef49f394add2a",
  "options": {
    "targetVisualNames": [
      "220b5550a5b947fbcc0c"
    ]
  },
  "explorationState": {
    "version": "1.3",
    "activeSection": "4afc6677f432ce8a2ac9",
    "sections": {
      "4afc6677f432ce8a2ac9": {
        "visualContainers": {
          "0c5ceb3cd88a6c008272": {
            "filters": {
              "byExpr": [
                {
                  "name": "688d304eaffd37818ec4",
                  "type": "Advanced",
                  "expression": {
                    "Measure": {
                      "Expression": {
                        "SourceRef": {
                          "Entity": "fact_ventas"
                        }
                      },
                      "Property": "% Variación ventas"
                    }
                  },
                  "howCreated": 0
                }
              ]
            },
            "singleVisual": {
              "visualType": "card",
              "objects": {}
            }
          },
          "146aa94f87a903df2472": {
            "filters": {
              "byExpr": [
                {
                  "name": "f12dbf48b9b6e96db70d",
                  "type": "Advanced",
                  "expression": {
                    "Measure": {
                      "Expression": {
                        "SourceRef": {
                          "Entity": "fact_ventas"
                        }
                      },
                      "Property": "ventas totales"
                    }
                  },
                  "howCreated": 0
                }
              ]
            },
            "singleVisual": {
              "visualType": "card",
              "objects": {}
            }
          },
          "19c4eee6e3c49ebd4658": {
            "filters": {
              "byExpr": [
                {
                  "name": "92b57a69d3b9111c9a96",
                  "type": "Advanced",
                  "expression": {
                    "Measure": {
                      "Expression": {
                        "SourceRef": {
                          "Entity": "fact_ventas"
                        }
                      },
                      "Property": "Ventas año anterior"
                    }
                  },
                  "howCreated": 0
                }
              ]
            },
            "singleVisual": {
              "visualType": "card",
              "objects": {}
            }
          },
          "1f857a1347582e29f4cb": {
            "singleVisual": {
              "visualType": "shape",
              "objects": {},
              "display": {
                "mode": "hidden"
              }
            }
          },
          "220b5550a5b947fbcc0c": {
            "singleVisual": {
              "visualType": "actionButton",
              "objects": {}
            }
          },
          "33fa7127f8dcece99775": {
            "filters": {
              "byExpr": [
                {
                  "name": "b035c1c854931ccfa7ec",
                  "type": "Advanced",
                  "expression": {
                    "Measure": {
                      "Expression": {
                        "SourceRef": {
                          "Entity": "fact_ventas"
                        }
                      },
                      "Property": "facturas"
                    }
                  },
                  "howCreated": 0
                }
              ]
            },
            "singleVisual": {
              "visualType": "card",
              "objects": {}
            }
          },
          "413302f53367cfb1e4d7": {
            "singleVisual": {
              "visualType": "actionButton",
              "objects": {},
              "display": {
                "mode": "hidden"
              }
            }
          },
          "46d2ab7c847159a9549f": {
            "filters": {
              "byExpr": [
                {
                  "name": "e78283a032f835e0150f",
                  "type": "Advanced",
                  "expression": {
                    "Measure": {
                      "Expression": {
                        "SourceRef": {
                          "Entity": "fact_ordenes"
                        }
                      },
                      "Property": "% Conversión pedidos"
                    }
                  },
                  "howCreated": 0
                }
              ]
            },
            "singleVisual": {
              "visualType": "card",
              "objects": {}
            }
          },
          "49a2defa00db3dd5719b": {
            "filters": {
              "byExpr": [
                {
                  "name": "8ca392d197a9aed2ef5b",
                  "type": "Advanced",
                  "expression": {
                    "HierarchyLevel": {
                      "Expression": {
                        "Hierarchy": {
                          "Expression": {
                            "PropertyVariationSource": {
                              "Expression": {
                                "SourceRef": {
                                  "Entity": "dim_fecha"
                                }
                              },
                              "Name": "Variación",
                              "Property": "FullDate"
                            }
                          },
                          "Hierarchy": "Jerarquía de fechas"
                        }
                      },
                      "Level": "Año"
                    }
                  },
                  "howCreated": 0
                },
                {
                  "name": "64b59564902cba1063ab",
                  "type": "Categorical",
                  "expression": {
                    "HierarchyLevel": {
                      "Expression": {
                        "Hierarchy": {
                          "Expression": {
                            "PropertyVariationSource": {
                              "Expression": {
                                "SourceRef": {
                                  "Entity": "dim_fecha"
                                }
                              },
                              "Name": "Variación",
                              "Property": "FullDate"
                            }
                          },
                          "Hierarchy": "Jerarquía de fechas"
                        }
                      },
                      "Level": "Mes"
                    }
                  },
                  "howCreated": 0
                },
                {
                  "name": "fb6ee498feea4f254506",
                  "type": "Advanced",
                  "expression": {
                    "Measure": {
                      "Expression": {
                        "SourceRef": {
                          "Entity": "fact_ventas"
                        }
                      },
                      "Property": "ventas totales"
                    }
                  },
                  "howCreated": 0
                },
                {
                  "name": "6e5b690573f1f1768236",
                  "type": "Advanced",
                  "expression": {
                    "Measure": {
                      "Expression": {
                        "SourceRef": {
                          "Entity": "fact_ventas"
                        }
                      },
                      "Property": "Ventas año anterior"
                    }
                  },
                  "howCreated": 0
                }
              ]
            },
            "singleVisual": {
              "visualType": "lineChart",
              "objects": {},
              "activeProjections": {
                "Category": [
                  {
                    "HierarchyLevel": {
                      "Expression": {
                        "Hierarchy": {
                          "Expression": {
                            "PropertyVariationSource": {
                              "Expression": {
                                "SourceRef": {
                                  "Entity": "dim_fecha"
                                }
                              },
                              "Name": "Variación",
                              "Property": "FullDate"
                            }
                          },
                          "Hierarchy": "Jerarquía de fechas"
                        }
                      },
                      "Level": "Año"
                    }
                  },
                  {
                    "HierarchyLevel": {
                      "Expression": {
                        "Hierarchy": {
                          "Expression": {
                            "PropertyVariationSource": {
                              "Expression": {
                                "SourceRef": {
                                  "Entity": "dim_fecha"
                                }
                              },
                              "Name": "Variación",
                              "Property": "FullDate"
                            }
                          },
                          "Hierarchy": "Jerarquía de fechas"
                        }
                      },
                      "Level": "Mes"
                    }
                  }
                ]
              }
            }
          },
          "5560832bfa8c5c8716a4": {
            "filters": {
              "byExpr": [
                {
                  "name": "0f399492b7be572e5c5f",
                  "type": "Advanced",
                  "expression": {
                    "Measure": {
                      "Expression": {
                        "SourceRef": {
                          "Entity": "fact_ventas"
                        }
                      },
                      "Property": "% margen"
                    }
                  },
                  "howCreated": 0
                }
              ]
            },
            "singleVisual": {
              "visualType": "card",
              "objects": {}
            }
          },
          "56579863de2d60d57b54": {
            "filters": {
              "byExpr": [
                {
                  "name": "6092830d609b6566c349",
                  "type": "Advanced",
                  "expression": {
                    "Measure": {
                      "Expression": {
                        "SourceRef": {
                          "Entity": "fact_ordenes"
                        }
                      },
                      "Property": "órdenes pendientes"
                    }
                  },
                  "howCreated": 0
                }
              ]
            },
            "singleVisual": {
              "visualType": "card",
              "objects": {}
            }
          },
          "59e0768fa374b6eb4eca": {
            "singleVisual": {
              "visualType": "textbox",
              "objects": {}
            }
          },
          "6530c89f885ed3ec550a": {
            "singleVisual": {
              "visualType": "actionButton",
              "objects": {},
              "display": {
                "mode": "hidden"
              }
            }
          },
          "67d58b72963b4fe9d30c": {
            "singleVisual": {
              "visualType": "actionButton",
              "objects": {},
              "display": {
                "mode": "hidden"
              }
            }
          },
          "688281e72bbba8c30d35": {
            "filters": {
              "byExpr": [
                {
                  "name": "9d0dd30676638fa73330",
                  "type": "Advanced",
                  "expression": {
                    "Measure": {
                      "Expression": {
                        "SourceRef": {
                          "Entity": "fact_ventas"
                        }
                      },
                      "Property": "cantidad vendida (unidades)"
                    }
                  },
                  "howCreated": 0
                }
              ]
            },
            "singleVisual": {
              "visualType": "card",
              "objects": {}
            }
          },
          "6eda77f907dda67d1d12": {
            "singleVisual": {
              "visualType": "textbox",
              "objects": {}
            }
          },
          "7ab622961e77796bbe5b": {
            "filters": {
              "byExpr": [
                {
                  "name": "2b5ae2ba97fa4a915deb",
                  "type": "Advanced",
                  "expression": {
                    "Measure": {
                      "Expression": {
                        "SourceRef": {
                          "Entity": "fact_ventas"
                        }
                      },
                      "Property": "Variación ventas"
                    }
                  },
                  "howCreated": 0
                }
              ]
            },
            "singleVisual": {
              "visualType": "card",
              "objects": {}
            }
          },
          "7f6bc9d1ed4939e53dd8": {
            "filters": {
              "byExpr": [
                {
                  "name": "1870e98385f5ed85646c",
                  "type": "Advanced",
                  "expression": {
                    "Measure": {
                      "Expression": {
                        "SourceRef": {
                          "Entity": "fact_transacciones_cliente"
                        }
                      },
                      "Property": "clientes morosos"
                    }
                  },
                  "howCreated": 0
                }
              ]
            },
            "singleVisual": {
              "visualType": "card",
              "objects": {}
            }
          },
          "9484cf1eee1ca00038f9": {
            "filters": {
              "byExpr": [
                {
                  "name": "f2218afcf3d61e4d88eb",
                  "type": "Advanced",
                  "expression": {
                    "Measure": {
                      "Expression": {
                        "SourceRef": {
                          "Entity": "fact_ordenes"
                        }
                      },
                      "Property": "% Órdenes pendientes"
                    }
                  },
                  "howCreated": 0
                }
              ]
            },
            "singleVisual": {
              "visualType": "card",
              "objects": {}
            }
          },
          "96e0883d6b5a4c858724": {
            "filters": {
              "byExpr": [
                {
                  "name": "866d51b8cf97db937446",
                  "type": "Advanced",
                  "expression": {
                    "Measure": {
                      "Expression": {
                        "SourceRef": {
                          "Entity": "fact_ordenes"
                        }
                      },
                      "Property": "órdenes creadas"
                    }
                  },
                  "howCreated": 0
                }
              ]
            },
            "singleVisual": {
              "visualType": "card",
              "objects": {}
            }
          },
          "9d149b921ff01b97c3eb": {
            "singleVisual": {
              "visualType": "actionButton",
              "objects": {},
              "display": {
                "mode": "hidden"
              }
            }
          },
          "a320ae8440ff1961c7b5": {
            "filters": {
              "byExpr": [
                {
                  "name": "114df298e8be7287ae61",
                  "type": "Advanced",
                  "expression": {
                    "Measure": {
                      "Expression": {
                        "SourceRef": {
                          "Entity": "fact_ventas"
                        }
                      },
                      "Property": "utilidad total"
                    }
                  },
                  "howCreated": 0
                }
              ]
            },
            "singleVisual": {
              "visualType": "card",
              "objects": {}
            }
          },
          "cb7526aeee95c702666b": {
            "singleVisual": {
              "visualType": "actionButton",
              "objects": {},
              "display": {
                "mode": "hidden"
              }
            }
          },
          "e1cfbca525b54cbe7935": {
            "filters": {
              "byExpr": [
                {
                  "name": "3c475150e16d984fff8d",
                  "type": "Advanced",
                  "expression": {
                    "Measure": {
                      "Expression": {
                        "SourceRef": {
                          "Entity": "fact_transacciones_cliente"
                        }
                      },
                      "Property": "% clientes morosos"
                    }
                  },
                  "howCreated": 0
                }
              ]
            },
            "singleVisual": {
              "visualType": "card",
              "objects": {}
            }
          },
          "ea152cf45a48d3b8c89e": {
            "filters": {
              "byExpr": [
                {
                  "name": "a8b23d3945671f72e199",
                  "type": "Advanced",
                  "expression": {
                    "Measure": {
                      "Expression": {
                        "SourceRef": {
                          "Entity": "fact_ordenes"
                        }
                      },
                      "Property": "% Cumplimiento entrega"
                    }
                  },
                  "howCreated": 0
                }
              ]
            },
            "singleVisual": {
              "visualType": "card",
              "objects": {}
            }
          },
          "ef86affc76c9225e18d5": {
            "filters": {
              "byExpr": [
                {
                  "name": "5a9406c329db04b2ba67",
                  "type": "Advanced",
                  "expression": {
                    "Measure": {
                      "Expression": {
                        "SourceRef": {
                          "Entity": "fact_transacciones_cliente"
                        }
                      },
                      "Property": "saldo pendiente"
                    }
                  },
                  "howCreated": 0
                }
              ]
            },
            "singleVisual": {
              "visualType": "card",
              "objects": {}
            }
          },
          "f2eada01d5d4ad932c68": {
            "filters": {
              "byExpr": [
                {
                  "name": "ae119093b961a1b6508d",
                  "type": "Advanced",
                  "expression": {
                    "Measure": {
                      "Expression": {
                        "SourceRef": {
                          "Entity": "fact_ventas"
                        }
                      },
                      "Property": "ventas totales"
                    }
                  },
                  "howCreated": 0
                },
                {
                  "name": "95ea8fa9ecd57605e85e",
                  "type": "Advanced",
                  "expression": {
                    "HierarchyLevel": {
                      "Expression": {
                        "Hierarchy": {
                          "Expression": {
                            "PropertyVariationSource": {
                              "Expression": {
                                "SourceRef": {
                                  "Entity": "dim_fecha"
                                }
                              },
                              "Name": "Variación",
                              "Property": "FullDate"
                            }
                          },
                          "Hierarchy": "Jerarquía de fechas"
                        }
                      },
                      "Level": "Año"
                    }
                  },
                  "howCreated": 0
                },
                {
                  "name": "66316507fb0ad477d80e",
                  "type": "Categorical",
                  "expression": {
                    "HierarchyLevel": {
                      "Expression": {
                        "Hierarchy": {
                          "Expression": {
                            "PropertyVariationSource": {
                              "Expression": {
                                "SourceRef": {
                                  "Entity": "dim_fecha"
                                }
                              },
                              "Name": "Variación",
                              "Property": "FullDate"
                            }
                          },
                          "Hierarchy": "Jerarquía de fechas"
                        }
                      },
                      "Level": "Mes"
                    }
                  },
                  "howCreated": 0
                }
              ]
            },
            "singleVisual": {
              "visualType": "lineChart",
              "objects": {},
              "activeProjections": {
                "Category": [
                  {
                    "HierarchyLevel": {
                      "Expression": {
                        "Hierarchy": {
                          "Expression": {
                            "PropertyVariationSource": {
                              "Expression": {
                                "SourceRef": {
                                  "Entity": "dim_fecha"
                                }
                              },
                              "Name": "Variación",
                              "Property": "FullDate"
                            }
                          },
                          "Hierarchy": "Jerarquía de fechas"
                        }
                      },
                      "Level": "Año"
                    }
                  },
                  {
                    "HierarchyLevel": {
                      "Expression": {
                        "Hierarchy": {
                          "Expression": {
                            "PropertyVariationSource": {
                              "Expression": {
                                "SourceRef": {
                                  "Entity": "dim_fecha"
                                }
                              },
                              "Name": "Variación",
                              "Property": "FullDate"
                            }
                          },
                          "Hierarchy": "Jerarquía de fechas"
                        }
                      },
                      "Level": "Mes"
                    }
                  }
                ]
              }
            }
          },
          "fb40e9d2efa646c4d598": {
            "singleVisual": {
              "visualType": "textbox",
              "objects": {}
            }
          },
          "3c4bde3c85f42a33710b": {
            "singleVisual": {
              "visualType": "actionButton",
              "objects": {},
              "display": {
                "mode": "hidden"
              }
            }
          }
        }
      }
    },
    "objects": {}
  }
}